wimlib/__init__.py
wimlib/_global.py
wimlib/backend.py
wimlib/compression.py
wimlib/error.py
wimlib/file.py
wimlib/image.py
wimlib/info.py
wimlib/progress.py
pywimlib-0.1.2.dist-info/LICENSE
pywimlib-0.1.2.dist-info/METADATA
pywimlib-0.1.2.dist-info/WHEEL
pywimlib-0.1.2.dist-info/top_level.txt
pywimlib-0.1.2.dist-info/RECORD
